{"meta":{"icon":"AccountTree","description":"A data flow — how data moves between systems or services","keywords":"data flow integration pipeline event","tags":"software,development,architecture"},"jsonSchema":{"$schema":"http://json-schema.org/draft-07/schema#","title":"Data Flow","type":"object","required":["title","source","destination"],"properties":{"title":{"type":"string"},"description":{"type":"string"},"source":{"type":"string"},"destination":{"type":"string"},"dataType":{"type":"string"},"protocol":{"type":"string","enum":["REST","GraphQL","Event","Batch","gRPC","WebSocket","FTP","Database"]},"direction":{"type":"string","enum":["unidirectional","bidirectional"]},"frequency":{"type":"string"},"authentication":{"type":"string"},"notes":{"type":"string"}}}}
