{
  "meta": {
    "icon": "ToggleOn",
    "description": "A feature flag — a toggle controlling feature visibility per environment or rollout",
    "keywords": "feature flag toggle Split.io LaunchDarkly rollout",
    "tags": "software,development,operations",
    "sync": [],
    "supersededBy": [],
    "implements": [],
    "extends": []
  },
  "jsonSchema": {
    "$schema": "http://json-schema.org/draft-07/schema#",
    "title": "Feature Flag",
    "type": "object",
    "required": [
      "name",
      "flagKey"
    ],
    "properties": {
      "name": {
        "x-id": "bb4a4070-6372-4e08-a778-f1139fc45996",
        "type": "string"
      },
      "flagKey": {
        "x-id": "0520d4c6-07e7-4c9e-ba57-9ceed9b26186",
        "type": "string"
      },
      "description": {
        "x-id": "494022f2-18ce-41c8-9969-df1588f65001",
        "type": "string"
      },
      "platform": {
        "x-id": "d8b6a65b-5225-453e-a22d-1a4bdc18500b",
        "type": "string",
        "enum": [
          "Split.io",
          "LaunchDarkly",
          "Unleash",
          "Custom"
        ]
      },
      "owner": {
        "x-id": "fbf7fa6c-c7cc-45cc-97b2-d4f866962970",
        "type": "string",
        "format": "email"
      },
      "status": {
        "x-id": "d561670c-5ae9-4719-b84c-0c97912b1349",
        "type": "string",
        "enum": [
          "enabled",
          "disabled",
          "rollout"
        ]
      },
      "rolloutPercentage": {
        "x-id": "542a99d2-c054-417b-9982-cc8b826ca6ed",
        "type": "number",
        "minimum": 0,
        "maximum": 100
      },
      "linkedTickets": {
        "x-id": "548a7662-946c-461a-8abf-b0850ebb1ddf",
        "type": "array",
        "items": {
          "type": "string"
        }
      },
      "cleanupDate": {
        "x-id": "b5cb0d44-8d69-4edb-848f-3262615303ad",
        "type": "string",
        "format": "date"
      }
    }
  },
  "sqlSchema": [
    "CREATE TABLE \"obj_0411d6fb_3160_4db6_bd91_93c6260689b2\" (\n    item_id UUID NOT NULL,\n    \"name\" TEXT,\n    \"flag_key\" TEXT,\n    \"description\" TEXT,\n    \"platform\" TEXT,\n    \"owner\" TEXT,\n    \"status\" TEXT,\n    \"rollout_percentage\" TEXT,\n    \"linked_tickets\" TEXT[] NOT NULL DEFAULT '{}',\n    \"cleanup_date\" TEXT,\n    CONSTRAINT \"pk_obj_0411d6fb_3160_4db6_bd91_93c6260689b2\" PRIMARY KEY (item_id),\n    CONSTRAINT \"fk_0411d6fb31604db6_item\" FOREIGN KEY (item_id) REFERENCES items(id)\n)"
  ]
}
